main.py
mcp_douyin-0.1.0.dist-info/METADATA
mcp_douyin-0.1.0.dist-info/WHEEL
mcp_douyin-0.1.0.dist-info/entry_points.txt
mcp_douyin-0.1.0.dist-info/top_level.txt
mcp_douyin-0.1.0.dist-info/RECORD
