Metadata-Version: 2.4
Name: mcp_douyin
Version: 0.1.0
Summary: MCP server for downloading Douyin videos and extracting text
Author: anyue
License: MIT
Classifier: Development Status :: 3 - Alpha
Classifier: Intended Audience :: Developers
Classifier: License :: OSI Approved :: MIT License
Classifier: Programming Language :: Python :: 3
Classifier: Programming Language :: Python :: 3.10
Classifier: Programming Language :: Python :: 3.11
Classifier: Programming Language :: Python :: 3.12
Requires-Python: >=3.10
Requires-Dist: mcp[fastmcp]>=1.0.0
Requires-Dist: requests
Requires-Dist: ffmpeg-python
Requires-Dist: tqdm
Requires-Dist: dashscope
